genome_collector
