Metadata-Version: 1.0
Name: genome-collector
Version: 0.1.4
Summary: Easily download and store genomes and BLAST DBs from NCBI
Home-page: https://github.com/Edinburgh-Genome-Foundry/genome_collector
Author: Zulko
Author-email: UNKNOWN
License: MIT
Keywords: NCBI genomes TaxID BLAST
Platform: UNKNOWN
